{
  "user_email": "user@user.com",
  "user_id": "user_user_com_1758786470148",
  "account_created": "2025-09-25T07:47:50.148Z",
  "last_sync": "2025-09-25T07:47:50.148Z",
  "total_sessions": 1,
  "total_scans": 5,
  "sessions": [
    {
      "id": "scanner1758786318372",
      "location": "Pharmacology",
      "year": 2,
      "batch": "2022/2023",
      "dateTime": "2025-09-25T07:45:18.372Z",
      "formattedDateTime": "25/09/2025 10:45:18",
      "scans": [
        {
          "id": "1758786357101",
          "content": "221904",
          "timestamp": "2025-09-25T07:45:57.101Z",
          "formattedTime": "10:45:57",
          "time": "2025-09-25T07:45:57.101Z",
          "isManual": false
        },
        {
          "id": "1758786394688",
          "content": "221948",
          "timestamp": "2025-09-25T07:46:34.688Z",
          "formattedTime": "10:46:34",
          "time": "2025-09-25T07:46:34.688Z",
          "isManual": true
        },
        {
          "id": "1758786416878",
          "content": "221911",
          "timestamp": "2025-09-25T07:46:56.878Z",
          "formattedTime": "10:46:56",
          "time": "2025-09-25T07:46:56.878Z",
          "isManual": true
        },
        {
          "id": "1758786452505",
          "content": "221779",
          "timestamp": "2025-09-25T07:47:32.504Z",
          "formattedTime": "10:47:32",
          "time": "2025-09-25T07:47:32.504Z",
          "isManual": true
        },
        {
          "id": "1758786470033",
          "content": "222035",
          "timestamp": "2025-09-25T07:47:50.033Z",
          "formattedTime": "10:47:50",
          "time": "2025-09-25T07:47:50.033Z",
          "isManual": true
        }
      ],
      "inProgress": true,
      "isScanner": true,
      "sessionType": "scanner",
      "recoveryStatus": "in_progress",
      "isChecklist": false,
      "user_email": "user@user.com",
      "user_id": "user_user_com_1758786470148",
      "created_by": "user@user.com",
      "created_at": "2025-09-25T07:47:50.148Z",
      "updated_at": "2025-09-25T07:47:50.148Z"
    }
  ]
}